{
  "schema_version": 1,
  "language": "es",
  "skills": {
    "vocabulary_description": {
      "mastery": 0.4625,
      "confidence": 0.1,
      "scaffold_need": 0.3,
      "last_seen": null
    },
    "agreement": {
      "mastery": 0.42781250000000004,
      "confidence": 0.19,
      "scaffold_need": 0.3,
      "last_seen": null
    },
    "past_narration": {
      "mastery": 0.42781250000000004,
      "confidence": 0.19,
      "scaffold_need": 0.55,
      "last_seen": "2026-03-06T20:02:16.955078+00:00"
    },
    "conditional_future": {
      "mastery": 0.42781250000000004,
      "confidence": 0.19,
      "scaffold_need": 0.55,
      "last_seen": "2026-03-06T20:02:16.955078+00:00"
    }
  },
  "updated_at": "2026-03-06T20:03:35.053912+00:00"
}
